ofxstatement_qif/__init__.py
ofxstatement_qif/plugin.py
ofxstatement_qif-0.6.0.dist-info/METADATA
ofxstatement_qif-0.6.0.dist-info/WHEEL
ofxstatement_qif-0.6.0.dist-info/entry_points.txt
ofxstatement_qif-0.6.0.dist-info/top_level.txt
ofxstatement_qif-0.6.0.dist-info/RECORD
