Metadata-Version: 2.1
Name: ofxstatement-qif
Version: 0.6.0
Summary: ofxstatement plugin for QIF files
Author-email: R Vadai <rvadai@segence.com>
Project-URL: repository, https://github.com/robvadai/ofxstatement-qif
Classifier: Development Status :: 3 - Alpha
Classifier: License :: OSI Approved :: MIT License
Classifier: Natural Language :: English
Classifier: Operating System :: OS Independent
Classifier: Programming Language :: Python
Classifier: Programming Language :: Python :: 3.8
Classifier: Programming Language :: Python :: 3.9
Requires-Python: >=3.8
Requires-Dist: quiffen ==2.0.11
Requires-Dist: pydantic ==1.10.17
Requires-Dist: numpy ==1.26.4
Provides-Extra: dev
Requires-Dist: ofxstatement ==0.9.1 ; extra == 'dev'
Requires-Dist: pytest ==8.2.0 ; extra == 'dev'
Requires-Dist: pytest-cov ==5.0.0 ; extra == 'dev'
Requires-Dist: prospector ==1.10.3 ; extra == 'dev'
Requires-Dist: bandit ==1.7.8 ; extra == 'dev'
Requires-Dist: setuptools ==69.5.1 ; extra == 'dev'
Requires-Dist: build ==1.2.1 ; extra == 'dev'
Requires-Dist: black ==24.4.2 ; extra == 'dev'
